iec60063/__init__.py
iec60063-0.2.dist-info/LICENSE
iec60063-0.2.dist-info/METADATA
iec60063-0.2.dist-info/WHEEL
iec60063-0.2.dist-info/top_level.txt
iec60063-0.2.dist-info/RECORD
